{"0001125": ["201.", "Benicio Del Toro"], "0000102": ["202.", "Kevin Bacon"], "0000664": ["203.", "Patrick Swayze"], "0000323": ["204.", "Michael Caine"], "0000380": ["205.", "Robert Duvall"], "0000044": ["206.", "Burt Lancaster"], "0000053": ["207.", "Robert Mitchum"], "0268199": ["208.", "Colin Farrell"], "0000034": ["209.", "William Holden"], "0000064": ["210.", "Edward G. Robinson"], "0001635": ["211.", "William Powell"], "0001467": ["212.", "Jared Leto"], "0001224": ["213.", "Errol Flynn"], "0000050": ["214.", "Groucho Marx"], "0000051": ["215.", "James Mason"], "0000036": ["216.", "Buster Keaton"], "0000080": ["217.", "Orson Welles"], "0000001": ["218.", "Fred Astaire"], "0177896": ["219.", "Bradley Cooper"], "0000198": ["220.", "Gary Oldman"], "0000179": ["221.", "Jude Law"], "0316079": ["222.", "Paul Giamatti"], "0000553": ["223.", "Liam Neeson"], "0000354": ["224.", "Matt Damon"], "1055413": ["225.", "Michael Fassbender"], "0000993": ["226.", "Carol Burnett"], "0001788": ["227.", "Jessica Tandy"], "0000166": ["228.", "Helen Hunt"], "0000099": ["229.", "Patricia Arquette"], "0000544": ["230.", "Carmen Miranda"], "0005028": ["231.", "Kate Hudson"], "0001876": ["232.", "Catherine Zeta-Jones"], "0000139": ["233.", "Cameron Diaz"], "0001666": ["234.", "Debbie Reynolds"], "0000995": ["235.", "Ellen Burstyn"], "0000058": ["236.", "Maureen O'Hara"], "0001485": ["237.", "Myrna Loy"], "0372176": ["238.", "Lena Headey"], "0001057": ["239.", "Toni Collette"], "0001473": ["240.", "Laura Linney"], "0000017": ["241.", "Marlene Dietrich"], "0001479": ["242.", "Carole Lombard"], "0000795": ["243.", "Jean Arthur"], "0001318": ["244.", "Jean Harlow"], "0001677": ["245.", "Ginger Rogers"], "0681933": ["246.", "Mary Pickford"], "0922213": ["247.", "Mae West"], "0000096": ["248.", "Gillian Anderson"], "0914612": ["249.", "Emma Watson"], "0000212": ["250.", "Meg Ryan"], "0000273": ["251.", "Alan Arkin"], "0000621": ["252.", "Kurt Russell"], "0350453": ["253.", "Jake Gyllenhaal"], "0331516": ["254.", "Ryan Gosling"], "0000147": ["255.", "Colin Firth"], "0004937": ["256.", "Jamie Foxx"], "0004778": ["257.", "Adrien Brody"], "0000905": ["258.", "Roberto Benigni"], "0000460": ["259.", "Jeremy Irons"], "0000719": ["260.", "F. Murray Abraham"], "0000377": ["261.", "Richard Dreyfuss"], "0002075": ["262.", "Peter Finch"], "0138770": ["263.", "Art Carney"], "0731772": ["264.", "Cliff Robertson"], "0001511": ["265.", "Lee Marvin"], "0001322": ["266.", "Rex Harrison"], "0000063": ["267.", "Anthony Quinn"], "0001703": ["268.", "Maximilian Schell"], "0362766": ["269.", "Tom Hardy"], "0000057": ["270.", "David Niven"], "0000458": ["271.", "William Hurt"], "0000989": ["272.", "Yul Brynner"], "0000308": ["273.", "Ernest Borgnine"], "1212722": ["274.", "Benedict Cumberbatch"], "0001768": ["275.", "Rod Steiger"], "1631269": ["276.", "Chlo\u00eb Grace Moretz"], "0447695": ["277.", "Anna Kendrick"], "0001833": ["278.", "Emily Watson"], "0000307": ["279.", "Helena Bonham Carter"], "0461136": ["280.", "Keira Knightley"], "0005490": ["281.", "Alexis Thorpe"], "0203836": ["282.", "Marion Davies"], "0424060": ["283.", "Scarlett Johansson"], "0266824": ["284.", "Dakota Fanning"], "0000098": ["285.", "Jennifer Aniston"], "0000124": ["286.", "Jennifer Connelly"], "1046097": ["287.", "Rachel McAdams"], "1659547": ["288.", "Carey Mulligan"], "0005109": ["289.", "Mila Kunis"], "1086543": ["290.", "Amanda Seyfried"], "0000182": ["291.", "Jennifer Lopez"], "0000117": ["292.", "Neve Campbell"], "0000103": ["293.", "Fairuza Balk"], "0004695": ["294.", "Jessica Alba"], "0829576": ["295.", "Kristen Stewart"], "0910278": ["296.", "Julie Walters"], "1913734": ["297.", "Rooney Mara"], "0000130": ["298.", "Jamie Lee Curtis"], "1297015": ["299.", "Emma Stone"], "0000379": ["300.", "Kirsten Dunst"]}