{"9202810": "Tau Ceti Four", "12026710": "Suspicion", "4532038": "The War with Grandpa", "7949204": "Chambers", "2372251": "Down a Dark Hall", "5212822": "Imposters", "4003440": "The House That Jack Built", "4685806": "The Con is On", "2503944": "Burnt", "3476576": "The Slap", "0397306": "American Dad!", "4095186": "Jump!", "4126604": "The Gift", "4126616": "The Mundane Goddess", "1937390": "Nymphomaniac: Vol. I", "2382009": "Nymphomaniac: Vol. II", "1333125": "Movie 43", "1540128": "Playing for Keeps", "1825133": "Smash", "1440732": "Bel Ami", "1341341": "Ceremony", "0814255": "Percy Jackson & the Olympians: The Lightning Thief", "1220220": "Motherhood", "1292569": "A Muppets Christmas: Letters to Santa", "1056101": "My Zinc Bed", "0809504": "The Accidental Husband", "0815178": "The Life Before Her Eyes", "0972390": "Mission Zero", "0465624": "My Super Ex-Girlfriend", "0395251": "The Producers", "0444736": "The Naked Brothers Band: The Movie", "0387514": "Prime", "0377471": "Be Cool", "0378194": "Kill Bill: Vol. 2", "0338337": "Paycheck", "0266697": "Kill Bill: Vol. 1", "0290664": "Hysterical Blindness", "0226935": "Chelsea Walls", "0275719": "Tape", "0200669": "The Golden Bowl", "0190861": "Vatel", "0158371": "Sweet and Lowdown", "0118661": "The Avengers", "0119683": "Les Mis\u00e9rables", "0119177": "Gattaca", "0118688": "Batman & Robin", "0116349": "Four Tales of Two Cities", "0112910": "Duke of Groove", "0117979": "The Truth About Cats & Dogs", "0115639": "Beautiful Girls", "0113849": "A Month by the Lake", "0110912": "Pulp Fiction", "7200744": "K.D. Lang: Just Keep Me Moving", "0106834": "Even Cowgirls Get the Blues", "0107473": "Mad Dog and Glory", "0104549": "Jennifer 8", "0104265": "Final Analysis", "6242230": "Dylan Thomas", "0102797": "Robin Hood", "0099762": "Henry & June", "0100924": "Where the Heart Is", "0094947": "Dangerous Liaisons", "0096764": "The Adventures of Baron Munchausen", "0095409": "Johnny Be Good", "0093351": "Kiss Daddy Goodnight", "0087544": "Nausica\u00e4 of the Valley of the Wind"}