{"13230326": "She Will Rise", "12547822": "Run Rabbit Run", "2953250": "The Shining Girls", "10767052": "Next Goal Wins", "8847712": "The French Dispatch", "5834204": "The Handmaid's Tale", "13051974": "Hormigueddon", "1051906": "The Invisible Man", "8430598": "Shirley", "5822564": "The Kitchen", "6857112": "Us", "6063090": "Light of My Life", "11971630": "Brandi Carlile: Party of One", "7942742": "Her Smell", "2837574": "The Old Man & the Gun", "4682136": "The Seagull", "2103085": "Top of the Lake", "4995790": "The Square", "5716624": "Tokyo Project", "4687410": "Mad to Be Normal", "1610525": "Chuck", "3517044": "The Free World", "0462335": "High-Rise", "3859076": "Truth", "0804503": "Mad Men", "3529656": "Meadowland", "3993894": "Queen of Earth", "4177974": "Couples Therapy", "2756032": "The One I Love", "3093546": "Listen Up Philip", "0096697": "The Simpsons", "0337692": "On the Road", "1730687": "Darling Companion", "0469152": "Smoking Nonsmoking", "1683043": "Green Lantern: Emerald Knights", "2040257": "A Buddy Story", "1226229": "Get Him to the Greek", "1314228": "Did You Hear About the Morgans?", "1442435": "Mercy", "9646364": "The Pack", "0072562": "Saturday Night Live", "1112285": "Fear Itself", "0878700": "New Orleans, Mon Amour", "0884038": "El camino", "0460644": "Ghost Whisperer", "0485857": "The Attic", "1147739": "Honored", "0768183": "Day Zero", "0412175": "Medium", "0996531": "They Never Found Her", "0413573": "Grey's Anatomy", "0275140": "Law & Order: Criminal Intent", "0200276": "The West Wing", "0460651": "Invasion", "0418511": "Bittersweet Place", "0406429": "Law & Order: Trial by Jury", "0338188": "The Missing", "0118437": "The Practice", "0368411": "Virgin", "0290086": "Temptation", "0279037": "Heart of America", "0283680": "West of Here", "0292698": "Spirit", "0172493": "Girl, Interrupted", "0149691": "Anywhere But Here", "0140397": "Mumford", "0139394": "The Joyriders", "0171259": "Earthly Possessions", "0407527": "Angelmaker", "0120323": "A Thousand Acres", "0173933": "It's Spring Training, Charlie Brown!", "0111970": "Freakazoid!", "0113613": "The Last Supper", "0111125": "Separate Lives", "0113931": "Naomi & Wynonna: Love Can Build a Bridge", "0112985": "Escape to Witch Mountain", "0103512": "Picket Fences", "0110115": "Imaginary Crimes", "0107065": "Gypsy", "0105941": "Animaniacs", "0106040": "Johnny Bago", "0107745": "Once Upon a Forest", "0286912": "Recycle Rex", "0103359": "Batman: The Animated Series", "0106973": "Frosty Returns", "0104865": "Midnight's Child", "0096534": "Anything But Love", "0103003": "Suburban Commando", "0102714": "Prison Stories: Women on the Inside", "0098832": "Lucky Chances", "0139053": "Bar Girls"}