{"7736460": "Newsflash", "10168312": "What If...?", "0425118": "I Know This Much Is True", "9071322": "Dark Waters", "4154796": "Avengers: Endgame", "4154664": "Captain Marvel", "4154756": "Avengers: Infinity War", "3501632": "Thor: Ragnarok", "6016776": "Team Thor", "3110958": "Now You See Me 2", "1895587": "Spotlight", "2395427": "Avengers: Age of Ultron", "1684226": "The Normal Heart", "1100089": "Foxcatcher", "1969062": "Infinitely Polar Bear", "1980929": "Begin Again", "1670345": "Now You See Me", "1300854": "Iron Man 3", "1932718": "Thanks for Sharing", "0848228": "The Avengers", "0466893": "Margaret", "1279935": "Date Night", "1130884": "Shutter Island", "0842926": "The Kids Are All Right", "1270277": "Sympathy for Delicious", "0386117": "Where the Wild Things Are", "1133991": "What Doesn't Kill You", "0844286": "The Brothers Bloom", "0861689": "Blindness", "0831884": "Reservation Road", "0443706": "Zodiac", "0905979": "Chicago 10", "0405676": "All the King's Men", "0398375": "Rumor Has It...", "0425123": "Just Like Heaven", "4693252": "13 Going on 30: Bloopers", "0369339": "Collateral", "0337563": "13 Going on 30", "0338013": "Eternal Sunshine of the Spotless Mind", "0361309": "We Don't Live Here Anymore", "0199626": "In the Cut", "0264150": "View from the Top", "0314412": "My Life Without Me", "0245562": "Windtalkers", "0245573": "XX/XY", "0272020": "The Last Castle", "0156741": "Apartment 12", "0231013": "The Beat", "0144142": "Committed", "0203230": "You Can Count on Me", "0431816": "How Does Anyone Get Old?", "0134154": "Ride with the Devil", "0159276": "Houdini", "0120577": "54", "0120813": "Safe Men", "0126908": "A Fish in the Bathtub", "0129359": "On the 2nd Day of Christmas", "0161743": "The Last Big Thing", "0115709": "Blood Money", "0116075": "The Dentist", "0116088": "The Destiny of Marty Fine", "0199772": "Mirror Mirror 3: The Voyeur", "0108756": "Due South", "0108320": "There Goes My Baby", "0109897": "A Gift from Heaven", "0110530": "Mirror Mirror 2: Raven Dance", "0108189": "A Song for You", "0111024": "Rough Trade", "0346222": "CBS Summer Playhouse"}