{"2538778": "Diamond Cartel", "1587685": "Decline of an Empire", "1566501": "For Greater Glory: The True Story of Cristiada", "1514043": "Highway to Hell", "0907731": "Eager to Die", "1013119": "Iron Road", "0999872": "Thomas Kinkade's Christmas Cottage", "1135968": "My Talks with Dean Spanley", "0758790": "The Tudors", "0486655": "Stardust", "0382932": "Ratatouille", "3492560": "Vanity Fair: Killers Kill, Dead Men Die", "0430431": "One Night with the King", "0489327": "Venus", "0431213": "Lassie", "0427042": "Casanova", "0332452": "Troy", "0340529": "Imperium: Augustus", "0346293": "Hitler: The Rise of Evil", "0325123": "Bright Young Things", "0243904": "The Final Curtain", "0269281": "Rock My World", "0285356": "The Education of Max Bickford", "5654494": "You Can", "0278521": "Jeffrey Bernard Is Unwell", "0178145": "Joan of Arc", "0165196": "Molokai", "0182306": "The Manor", "0158653": "Coming Home", "0119891": "Phantoms", "0119095": "FairyTale: A True Story", "0066684": "Masterpiece Classic", "0115195": "Gulliver's Travels", "0111998": "Heavy Weather", "0108823": "North & South: Book 3, Heaven & Hell", "0105361": "The Seventh Coin", "0182008": "Civvies", "0105222": "Rebecca's Daughters", "0102130": "Isabelle Eberhardt", "0102216": "King Ralph", "0100281": "The Nutcracker Prince", "0100456": "The Rainbow Thief", "0098658": "Wings of Fame", "0099322": "The Pied Piper", "0097574": "Up to Date", "0101659": "Uncle Silas", "0095304": "High Spirits", "0093389": "The Last Emperor", "0090856": "Club Paradise", "0088591": "The Ray Bradbury Theater", "0088960": "Creator", "0088206": "Supergirl", "0087557": "Kim", "0190673": "Pygmalion", "0086399": "Svengali", "0272842": "Sherlock Holmes and the Baskerville Curse", "0238595": "Sherlock Holmes and a Study in Scarlet", "0238597": "Sherlock Holmes and the Valley of Fear", "0238596": "Sherlock Holmes and the Sign of Four", "0121516": "Man and Superman", "0084370": "My Favorite Year", "0081900": "Masada", "0233110": "Strumpet City", "0081568": "The Stunt Man", "0080491": "Caligula", "0080180": "Zulu Dawn", "0078105": "Power Play", "0075151": "Rogue Male", "0073014": "The Far Side of Paradise", "0074849": "Man Friday", "0073637": "Rosebud", "0068909": "Man of La Mancha", "0069198": "The Ruling Class", "0070854": "Under Milk Wood", "0067458": "Murphy's War", "0065581": "Brotherly Love", "0064382": "Goodbye, Mr. Chips", "0063034": "Great Catherine", "0063227": "The Lion in Winter", "0061452": "Casino Royale", "0914702": "ITV Play of the Week", "0062038": "The Night of the Generals", "0060164": "The Bible: In the Beginning...", "0060522": "How to Steal a Million", "0059674": "The Sandpiper", "0059903": "What's New Pussycat", "0059399": "Lord Jim", "0057877": "Becket", "0056172": "Lawrence of Arabia", "0050054": "Rendezvous", "0053752": "The Day They Robbed the Bank of England", "0053244": "The Savage Innocents", "3665496": "Siwan: The King's Daughter", "0053994": "Kidnapped", "5188474": "Theatre Night", "0989125": "BBC Sunday-Night Theatre", "1669808": "The Castiglioni Brothers", "0161126": "Armchair Theatre", "0051310": "The Scarlet Pimpernel"}