{"2401256": "The Night Of", "1600196": "The Drop", "2390361": "Enough Said", "2312862": "Nicky Deuce", "0790628": "The Incredible Burt Wonderstone", "1790885": "Zero Dark Thirty", "1230215": "Not Fade Away", "1764234": "Killing Them Softly", "1634136": "Violet & Daisy", "1623742": "Cinema Verite", "1155060": "Down the Shore", "1587419": "Mint Julep", "1183923": "Welcome to the Rileys", "0386117": "Where the Wild Things Are", "1111422": "The Taking of Pelham 123", "1226774": "In the Loop", "1591613": "Stories USA", "0141842": "The Sopranos", "0484895": "The Sopranos: Road to Respect", "0857366": "Club Soda", "0405676": "All the King's Men", "0441774": "Lonely Hearts", "6672978": "The Sopranos: Season 6 Invitation to the Set", "0368222": "Romance & Cigarettes", "0252028": "Surviving Christmas", "0272020": "The Last Castle", "0243133": "The Man Who Wasn't There", "0236493": "The Mexican", "0300653": "A Whole New Day", "0134273": "8MM", "0120633": "A Civil Action", "0119670": "The Mighty", "0119099": "Fallen", "0119668": "Midnight in the Garden of Good and Evil", "0119879": "Dance with the Devil", "0118528": "12 Angry Men", "0120112": "She's So Lovely", "0118330": "Gun", "0119783": "Night Falls on Manhattan", "0116731": "The Juror", "0113161": "Get Shorty", "0112740": "Crimson Tide", "0114009": "New World", "0111400": "Terminal Velocity", "0109129": "Angie", "0207554": "Italian Movie", "0107613": "Mr. Wonderful", "0108399": "True Romance", "0107594": "Money for Nothing", "0105483": "A Stranger Among Us", "0102266": "The Last Boy Scout", "0093959": "Shock! Shock! Shock!"}