{"0085271": "Brainstorm", "0081758": "Willie & Phil", "0081151": "The Memory of Eva Ryker", "0081032": "The Last Married Couple in America", "0079550": "Meteor", "0078622": "Hart to Hart", "0079005": "The Cracker Factory", "0078616": "From Here to Eternity", "0072574": "Switch", "0074295": "Cat on a Hot Tin Roof", "0073526": "Peeper", "0069681": "The Affair", "0068334": "The Candidate", "0064100": "Bob & Carol & Ted & Alice", "0060818": "Penelope", "0061089": "This Property Is Condemned", "0059314": "Inside Daisy Clover", "0059243": "The Great Race", "0058580": "Sex and the Single Girl", "0057263": "Love with the Proper Stranger", "0056048": "Gypsy", "0055614": "West Side Story", "0055471": "Splendor in the Grass", "0053582": "All the Fine Young Cannibals", "0052680": "Cash McCall", "0051819": "Kings Go Forth", "0051911": "Marjorie Morningstar", "0050204": "Bombers B-52", "0046648": "Studio 57", "0188323": "Conflict", "0049264": "The Girl He Left Behind", "0048880": "The Kaiser Aluminum Hour", "0049036": "The Burning Hills", "0049110": "A Cry in the Night", "0047786": "Warner Brothers Presents", "0049730": "The Searchers", "0047748": "Kings Row", "0271280": "Camera Three", "0040051": "Studio One in Hollywood", "0045395": "General Electric Theater", "0048545": "Rebel Without a Cause", "2276770": "Max Liebman Spectaculars", "0048448": "One Desire", "0041024": "The Ford Television Theatre", "0044263": "Four Star Playhouse", "0046622": "Mayor of the Town", "0047494": "The Silver Chalice", "1144653": "The Reluctant Redeemer", "0046638": "Public Defender", "0045430": "The Pepsi-Cola Playhouse", "0045434": "The Pride of the Family", "0045186": "The Star", "0044782": "Just for You", "0045104": "The Rose Bowl Story", "0374449": "The Schaefer Century Theatre", "2380776": "Chevron Theatre", "0043350": "The Blue Veil", "0039123": "Kraft Theatre", "0043457": "Dear Brat", "0042610": "The Jackpot", "0042784": "Never a Dull Moment", "0042819": "Our Very Own", "0042790": "No Sad Songs for Me", "0041350": "Father Was a Fullback", "0041431": "The Green Promise", "0040229": "Chicken Every Sunday", "0040762": "Scudda Hoo! Scudda Hay!", "0039341": "Driftwood", "0039628": "Miracle on 34th Street", "0039420": "The Ghost and Mrs. Muir", "0038383": "The Bride Wore Boots", "0039041": "Tomorrow Is Forever", "0035970": "Happy Land", "0036170": "The Moon Is Down"}