{"11700260": "Official Competition", "8385148": "The Hitman's Wife's Bodyguard", "1464335": "Uncharted", "6673612": "Dolittle", "5865326": "The Laundromat", "10916366": "El Hormiguero: Vacaciones en el Titanic", "8291806": "Pain and Glory", "5989218": "Life Itself", "8944244": "Asesinato en el Hormiguero Express", "5673782": "Genius", "5629524": "Beyond the Edge", "6204340": "Bullet Head", "6288694": "Acts of Vengeance", "3910736": "Gun Shy", "3244786": "The Music of Silence", "2090465": "Black Butterfly", "3501112": "Security", "3014910": "Finding Altamira", "2006295": "The 33", "2101383": "Knight of Cups", "2279373": "The SpongeBob Movie: Sponge Out of Water", "1971325": "Automata", "2333784": "The Expendables 3", "2002718": "Machete Kills", "1639826": "Justin and the Knights of Valour", "2243389": "I'm So Excited!", "2111994": "This American Housewife", "1839492": "Ruby Sparks", "2268617": "Puss in Boots: The Three Diablos", "1506999": "Haywire", "1701210": "Day of the Falcon", "0448694": "Puss in Boots", "1517489": "Spy Kids 4-D: All the Time in the World", "1189073": "The Skin I Live In", "9583666": "Shrek's Yule Log", "1830577": "Donkey's Christmas Shrektacular", "1307873": "The Big Bang", "1725156": "Scared Shrekless", "1182350": "You Will Meet a Tall Dark Stranger", "0892791": "Shrek Forever After", "1112782": "Thick as Thieves", "0974613": "The Other Man", "0780534": "My Mom's New Boyfriend", "0897387": "Shrek the Halls", "0413267": "Shrek the Third", "0445935": "Bordertown", "1695145": "Take the Lead: Making-of Documentary", "0446046": "Take the Lead", "0386140": "The Legend of Zorro", "0438844": "Far Far Away Idol", "0298148": "Shrek 2", "0314197": "Imagining Argentina", "0337824": "And Starring Pancho Villa as Himself", "0285823": "Once Upon a Time in Mexico", "0338459": "Spy Kids 3-D: Game Over", "0308208": "Ballistic: Ecks vs. Sever", "0120679": "Frida", "0287717": "Spy Kids 2: Island of Lost Dreams", "0280665": "Femme Fatale", "0218922": "Original Sin", "0227538": "Spy Kids", "0201485": "The Body", "0196857": "Play It to the Bone", "0162766": "The White River Kid", "0120657": "The 13th Warrior", "0120746": "The Mask of Zorro", "10521134": "Sanpellegrino Calze", "0116250": "Evita", "0118001": "Two Much", "0113965": "Never Talk to Strangers", "0112401": "Assassins", "0113101": "Four Rooms", "0112851": "Desperado", "0113808": "Miami Rhapsody", "0110148": "Interview with the Vampire: The Vampire Chronicles", "0110712": "Of Love and Shadows", "0107818": "Philadelphia", "0107151": "The House of the Spirits", "0108670": "Outrage", "0107012": "Il giovane Mussolini", "2979006": "Cuentos de Borges", "0102477": "Una mujer bajo la lluvia", "0104802": "The Mambo Kings", "0103065": "Terra Nova", "0099298": "Against the Wind", "0095670": "La mujer de tu vida", "0092509": "El acto", "0101026": "Tie Me Up! Tie Me Down!", "0096938": "La blanca paloma", "0098324": "If They Tell You I Fell", "0094705": "Going Down in Morocco", "0094822": "Baton Rouge", "0093747": "El placer de matar", "0095675": "Women on the Verge of a Nervous Breakdown", "0090668": "As\u00ed como hab\u00edan sido", "0093412": "Law of Desire", "0090926": "Delirios de amor", "0090561": "27 horas", "0091805": "Puzzle", "0091495": "Matador", "0088887": "Caso cerrado", "0088954": "La corte de Fara\u00f3n", "0089946": "R\u00e9quiem por un campesino espa\u00f1ol", "0088443": "Los zancos", "0385415": "Fragmentos de interior", "0086293": "El se\u00f1or Gal\u00edndez", "0085308": "El caso Almer\u00eda", "0086612": "Y del seguro... l\u00edbranos Se\u00f1or!", "0084228": "Labyrinth of Passion", "0084490": "False Eyelash"}