{"2211910": "Mandrake the Magician", "13143964": "Borat Subsequent Moviefilm", "13327728": "Surprising Best Friend with Borat!!", "0320037": "Jimmy Kimmel Live!", "1070874": "The Trial of the Chicago 7", "5952634": "The Spy", "8679236": "Who Is America?", "6254730": "Past Forward", "2567026": "Alice Through the Looking Glass", "3381008": "The Brothers Grimsby", "1229340": "Anchorman 2: The Legend Continues", "0866442": "Eastbound & Down", "1707386": "Les Mis\u00e9rables", "1277953": "Madagascar 3: Europe's Most Wanted", "1645170": "The Dictator", "0115147": "The Daily Show", "0072562": "Saturday Night Live", "0970179": "Hugo", "0096697": "The Simpsons", "2866056": "Madonna: Celebration - The Video Collection", "0106053": "Late Show with David Letterman", "0889583": "Br\u00fcno", "0899126": "The Tonight Show with Conan O'Brien", "0479952": "Madagascar: Escape 2 Africa", "0408236": "Sweeney Todd: The Demon Barber of Fleet Street", "0474499": "Howard Stern on Demand", "0106052": "Late Night with Conan O'Brien", "1628029": "Reel Comedy", "0443453": "Borat: Cultural Learnings of America for Make Benefit Glorious Nation of Kazakhstan", "0415306": "Talladega Nights: The Ballad of Ricky Bobby", "0264235": "Curb Your Enthusiasm", "0351283": "Madagascar", "0462720": "Spyz", "7225576": "Ali G Feat. Shaggy: Me Julie", "0284837": "Ali G Indahouse", "0257818": "The Jolly Boys' Last Stand", "6673782": "Madonna: Music", "0926185": "Ali G's Christmas Message to the Nation", "0224452": "The 11 O'Clock Show", "0143033": "Comedy Nation", "0463359": "Punch", "0390137": "Jack and Jeremy's Police 4"}