{"9814900": "Trailer Park Boys: The Animated Series", "12107408": "Trailer Park Boys: Park After Dark", "3205334": "The Moodys", "11112140": "How to Train Your Dragon: Homecoming", "1925493": "Random Acts of Violence", "6515910": "The Kindness of Strangers", "2386490": "How to Train Your Dragon: The Hidden World", "8497646": "NKPC: New Kid Placement Committee", "7973154": "Silence", "4647692": "Letterkenny", "3869122": "The Magic School Bus Rides Again", "4816058": "Dragons: Race to the Edge", "7571260": "Robot Bullies", "2417712": "Goon: Last of the Enforcers", "4189492": "Man Seeking Woman", "4996022": "Lovesick", "4191768": "Dragons: Dawn of the Dragon Racers", "1646971": "How to Train Your Dragon 2", "1828968": "Don Peyote", "2325846": "DreamWorks Dragons", "1234721": "RoboCop", "6963396": "Dreamworks How to Train Your Dragon Legends", "2172985": "The Art of the Steal", "4434588": "The Real World: This Is the End Edition", "1245492": "This Is the End", "1480656": "Cosmopolis", "1595680": "Being Human", "2113625": "Book of Dragons", "2065968": "Dragons: Gift of the Night Fury", "1456635": "Goon", "1589889": "The Drunk and on Drugs Happy Funtime Hour", "1920083": "Marcy", "1744776": "Legend of the Boneknapper Dragon", "1576440": "Good Neighbours", "0963966": "The Sorcerer's Apprentice", "2542490": "Dreamworks How to Train Your Dragon Legends", "1621800": "How to Train Your Dragon", "0892769": "How to Train Your Dragon", "0815236": "She's Out of My League", "1295072": "The Trotsky", "1078912": "Night at the Museum: Battle of the Smithsonian", "0489049": "Fanboys", "0981227": "Nick and Norah's Infinite Playlist", "0942385": "Tropic Thunder", "0983909": "Real Time", "0906326": "Just Buried", "1568843": "Jay and Seth Versus the Apocalypse", "0478311": "Knocked Up", "0433309": "Numb3rs", "0460653": "Just Legal", "0464061": "I'm Reed Fish", "0475271": "Fetching Cody", "0369169": "The Stones", "0405159": "Million Dollar Baby", "0273028": "Undeclared", "0323571": "Nemesis Game", "0292644": "The Rules of Attraction", "0185936": "Matthew Blackheart: Monster Smasher", "0181875": "Almost Famous", "0103352": "Are You Afraid of the Dark?", "0184018": "Who Gets the House?", "0160800": "Running Home", "0115281": "My Hometown", "0179061": "The Worst Witch", "0169231": "The Sickroom"}